django_uuid7/__init__.py
django_uuid7/fields.py
django_uuid7/forms.py
django_uuid7/mixins.py
django_uuid7/serializers.py
django_uuid7/uuid7.py
django_uuid7-0.1.1.dist-info/LICENSE
django_uuid7-0.1.1.dist-info/METADATA
django_uuid7-0.1.1.dist-info/WHEEL
django_uuid7-0.1.1.dist-info/top_level.txt
django_uuid7-0.1.1.dist-info/RECORD
